optimal_data_splitter.py
optimal_data_splitter-0.1.3.dist-info/METADATA
optimal_data_splitter-0.1.3.dist-info/WHEEL
optimal_data_splitter-0.1.3.dist-info/RECORD
