Metadata-Version: 2.1
Name: optimal-data-splitter
Version: 0.1.3
Summary: Data splitting package
License: MIT
Author: Matthew Rockwood
Requires-Python: >=3.11,<4.0
Classifier: License :: OSI Approved :: MIT License
Classifier: Programming Language :: Python :: 3
Classifier: Programming Language :: Python :: 3.11
Requires-Dist: matplotlib (>=3.7.2,<4.0.0)
Requires-Dist: numpy (>=1.25.2,<2.0.0)
Requires-Dist: pandas (>=2.1.0,<3.0.0)
Requires-Dist: scikit-learn (>=1.3.0,<2.0.0)
